primonumber/__init__.py
primonumber-1.0.dist-info/LICENSE
primonumber-1.0.dist-info/METADATA
primonumber-1.0.dist-info/WHEEL
primonumber-1.0.dist-info/top_level.txt
primonumber-1.0.dist-info/RECORD
