Metadata-Version: 2.1
Name: primonumber
Version: 1.0
Summary: Muestra los numeros primos de un numero.
Home-page: UNKNOWN
Author: Jesús Gil
Author-email: jesusgil@jssistemas.es
License: GNU GPLv3
Keywords: mathematical operations
Platform: UNKNOWN
Classifier: Development Status :: 4 - Beta
Classifier: Intended Audience :: Developers
Classifier: Topic :: Utilities
Classifier: License :: OSI Approved :: GNU General Public License v3 (GPLv3)
Classifier: Programming Language :: Python :: 3
Classifier: Operating System :: OS Independent
License-File: LICENSE
